django_fast_export/__init__.py
django_fast_export/csv.py
django_fast_export-0.1.1.dist-info/LICENSE
django_fast_export-0.1.1.dist-info/METADATA
django_fast_export-0.1.1.dist-info/WHEEL
django_fast_export-0.1.1.dist-info/top_level.txt
django_fast_export-0.1.1.dist-info/RECORD
