Metadata-Version: 2.1
Name: django_fast_export
Version: 0.1.1
Summary: Fast exporting of data from the Django admin panel
Home-page: https://github.com/matthiask/django-fast-export/
Author: Matthias Kestenholz
Author-email: mk@feinheit.ch
License: MIT
Classifier: License :: OSI Approved :: MIT License
Classifier: Programming Language :: Python
Classifier: Programming Language :: Python :: 3
Classifier: Programming Language :: Python :: 3 :: Only
Classifier: Programming Language :: Python :: 3.8
Classifier: Programming Language :: Python :: 3.9
Classifier: Programming Language :: Python :: 3.10
Requires-Python: >=3.8
License-File: LICENSE
Requires-Dist: Django >=3.2
